LICENSE.txt
MANIFEST.in
README.rst
requirements.txt
setup.py
test_wordlist.txt
similar/__init__.py
similar/exceptions.py
similar/similar.py
similar.egg-info/PKG-INFO
similar.egg-info/SOURCES.txt
similar.egg-info/dependency_links.txt
similar.egg-info/requires.txt
similar.egg-info/top_level.txt